deepsearch/__init__.py
deepsearch/artifacts/.resources/artifact_management.drawio
deepsearch/artifacts/.resources/artifact_management.png
deepsearch/artifacts/README.md
deepsearch/artifacts/__init__.py
deepsearch/artifacts/artifact_manager.py
deepsearch/artifacts/cli/__init__.py
deepsearch/artifacts/cli/main.py
deepsearch/chemistry/__init__.py
deepsearch/chemistry/models.py
deepsearch/chemistry/queries/__init__.py
deepsearch/chemistry/queries/molecules.py
deepsearch/chemistry/queries/queries.py
deepsearch/chemistry/resources.py
deepsearch/cli.py
deepsearch/core/__init__.py
deepsearch/core/cli/__init__.py
deepsearch/core/cli/login.py
deepsearch/core/cli/main.py
deepsearch/core/cli/plugins.py
deepsearch/core/cli/profile.py
deepsearch/core/cli/profile_utils.py
deepsearch/core/cli/utils.py
deepsearch/core/client/__init__.py
deepsearch/core/client/config.py
deepsearch/core/client/settings.py
deepsearch/core/client/settings_manager.py
deepsearch/core/util/__init__.py
deepsearch/core/util/_version.py
deepsearch/core/util/cli_output.py
deepsearch/cps/__init__.py
deepsearch/cps/apis/.gitattributes
deepsearch/cps/apis/README.md
deepsearch/cps/apis/__init__.py
deepsearch/cps/apis/kg/__init__.py
deepsearch/cps/apis/kg/create/__init__.py
deepsearch/cps/apis/kg/create/api/__init__.py
deepsearch/cps/apis/kg/create/api/edges_api.py
deepsearch/cps/apis/kg/create/api/indices_api.py
deepsearch/cps/apis/kg/create/api/knowledge_graphs_api.py
deepsearch/cps/apis/kg/create/api/nodes_api.py
deepsearch/cps/apis/kg/create/api/tasks_api.py
deepsearch/cps/apis/kg/create/api_client.py
deepsearch/cps/apis/kg/create/configuration.py
deepsearch/cps/apis/kg/create/exceptions.py
deepsearch/cps/apis/kg/create/models/__init__.py
deepsearch/cps/apis/kg/create/models/database_source.py
deepsearch/cps/apis/kg/create/models/database_source_mongo.py
deepsearch/cps/apis/kg/create/models/database_source_s3.py
deepsearch/cps/apis/kg/create/models/edge_matrix.py
deepsearch_toolkit-2.0.1.dist-info/LICENSE
deepsearch_toolkit-2.0.1.dist-info/METADATA
deepsearch_toolkit-2.0.1.dist-info/WHEEL
deepsearch_toolkit-2.0.1.dist-info/entry_points.txt
deepsearch_toolkit-2.0.1.dist-info/RECORD
