Metadata-Version: 2.1
Name: deepsearch-toolkit
Version: 2.0.1
Summary: Interact with the Deep Search platform for new knowledge explorations and discoveries
Home-page: https://ds4sd.github.io/deepsearch-toolkit/
License: MIT
Keywords: deepsearch,convert,knowledge graph,discovery,nlp
Author: Michele Dolfi
Author-email: dol@zurich.ibm.com
Requires-Python: >=3.9,<4.0
Classifier: Development Status :: 5 - Production/Stable
Classifier: Intended Audience :: Developers
Classifier: Intended Audience :: Science/Research
Classifier: License :: OSI Approved :: MIT License
Classifier: Operating System :: OS Independent
Classifier: Programming Language :: Python :: 3
Classifier: Programming Language :: Python :: 3.9
Classifier: Programming Language :: Python :: 3.10
Classifier: Programming Language :: Python :: 3.11
Classifier: Programming Language :: Python :: 3.12
Classifier: Programming Language :: Python :: 3.13
Classifier: Typing :: Typed
Provides-Extra: all
Provides-Extra: api
Requires-Dist: anyio (>=3.6.2,<4.0.0) ; extra == "api" or extra == "all"
Requires-Dist: certifi (>=2024.07.04,<2025.0.0)
Requires-Dist: docling-core (>=2.0.0,<3.0.0)
Requires-Dist: fastapi (>=0.115.3,<0.116.0) ; extra == "api" or extra == "all"
Requires-Dist: platformdirs (>=3.5.1,<5.0.0)
Requires-Dist: pluggy (>=1.0.0,<2.0.0)
Requires-Dist: pydantic (>=2.0.3,<3.0.0)
Requires-Dist: pydantic-settings (>=2.4.0,<3.0.0)
Requires-Dist: python-dateutil (>=2.8.2,<3.0.0)
Requires-Dist: python-dotenv (>=1.0.0,<2.0.0)
Requires-Dist: requests (>=2.27.1,<3.0.0)
Requires-Dist: six (>=1.16.0,<2.0.0)
Requires-Dist: tabulate (>=0.8.9,<1.0.0)
Requires-Dist: tqdm (>=4.64.0,<5.0.0)
Requires-Dist: typer[all] (>=0.9.0,<1.0.0)
Requires-Dist: urllib3 (>=1.21.1,<3)
Requires-Dist: uvicorn (>=0.32.0) ; extra == "api" or extra == "all"
Project-URL: Bug Tracker, https://github.com/DS4SD/deepsearch-toolkit/issues
Project-URL: Documentation, https://ds4sd.github.io/deepsearch-toolkit/
Project-URL: Discussion forum, https://github.com/DS4SD/deepsearch-toolkit/discussions
Project-URL: Repository, https://github.com/DS4SD/deepsearch-toolkit
